cg_openmm/__init__.py
cg_openmm/build/__init__.py
cg_openmm/build/cg_build.py
cg_openmm/simulation/__init__.py
cg_openmm/simulation/rep_exch.py
cg_openmm/simulation/tools.py
cg_openmm/utilities/__init__.py
cg_openmm/utilities/iotools.py
cg_openmm/utilities/util.py
cg_openmm-1.0.dist-info/LICENSE
cg_openmm-1.0.dist-info/METADATA
cg_openmm-1.0.dist-info/WHEEL
cg_openmm-1.0.dist-info/top_level.txt
cg_openmm-1.0.dist-info/RECORD
