Metadata-Version: 2.1
Name: cg-openmm
Version: 1.0
Summary: Package containing tools to perform coarse-grained modeling in OpenMM.
Home-page: https://github.com/shirtsgroup/cg_openmm
Author: Garrett A. Meek
Author-email: garrett.a.meek@gmail.com
License: MIT
Platform: UNKNOWN
Classifier: License :: OSI Approved :: MIT License
Classifier: Programming Language :: Python
Classifier: Programming Language :: Python :: 3
Classifier: Programming Language :: Python :: 3.6
Classifier: Programming Language :: Python :: Implementation :: CPython
Classifier: Programming Language :: Python :: Implementation :: PyPy
Requires-Python: >=3.6.8
